[{"method_id":4,"script_path":"scripts\/sum.py","args":{"optical_u":10,"optical_v":9786,"optical_g":79786,"optical_r":786,"optical_i":6,"optical_z":98,"infrared_three_six":897,"infrared_four_five":6,"infrared_five_eight":54,"infrared_eight_zero":876,"infrared_J":978,"infrared_H":876,"infrared_K":76,"radio_one_four":9768},"unique_id":"5f9244f6a3fae","galaxy_id":305},{"method_id":4,"script_path":"scripts\/sum.py","args":{"optical_u":10,"optical_v":9786,"optical_g":79786,"optical_r":786,"optical_i":6,"optical_z":98,"infrared_three_six":897,"infrared_four_five":6,"infrared_five_eight":54,"infrared_eight_zero":876,"infrared_J":978,"infrared_H":876,"infrared_K":76,"radio_one_four":9768},"unique_id":"5f9244f6a3fbc","galaxy_id":306},{"method_id":4,"script_path":"scripts\/sum.py","args":{"optical_u":10,"optical_v":9786,"optical_g":79786,"optical_r":786,"optical_i":6,"optical_z":98,"infrared_three_six":897,"infrared_four_five":6,"infrared_five_eight":54,"infrared_eight_zero":876,"infrared_J":978,"infrared_H":876,"infrared_K":76,"radio_one_four":9768},"unique_id":"5f9244f6a3fc7","galaxy_id":307},{"method_id":4,"script_path":"scripts\/sum.py","args":{"optical_u":10,"optical_v":9786,"optical_g":79786,"optical_r":786,"optical_i":6,"optical_z":98,"infrared_three_six":897,"infrared_four_five":6,"infrared_five_eight":54,"infrared_eight_zero":876,"infrared_J":978,"infrared_H":876,"infrared_K":76,"radio_one_four":9768},"unique_id":"5f9244f6a3fce","galaxy_id":308},{"method_id":4,"script_path":"scripts\/sum.py","args":{"optical_u":10,"optical_v":9786,"optical_g":79786,"optical_r":786,"optical_i":6,"optical_z":98,"infrared_three_six":897,"infrared_four_five":6,"infrared_five_eight":54,"infrared_eight_zero":876,"infrared_J":978,"infrared_H":876,"infrared_K":76,"radio_one_four":9768},"unique_id":"5f9244f6a3fd5","galaxy_id":309}]